Metadata-Version: 2.1
Name: ESTUDOPOO
Version: 0.0.1
Summary: PRIMEIROS PROGRAMAS DE ESTUDO EM PY
Home-page: https://github.com/felipesoler-ads
Author: FELIPE SOLER
Author-email: FELIPESOLER12@GMAIL.COM
Requires-Python: >=3.8
